{
  "actions": {
    "move_left": [
      {
        "button": "Left",
        "device":  "Keyboard",
        "hold": false,
        "doube_tap": false
      },
      {
        "button": "A",
        "device": "Keyboard",
        "hold": false,
        "doube_tap": false
      }
    ],
    "move_right": [
      {
        "button": "Right",
        "device": "Keyboard",
        "hold": false,
        "doube_tap": false
      },
      {
        "button": "D",
        "device": "Keyboard",
        "hold": false,
        "doube_tap": false
      }
    ],
    "move_down": [
      {
        "button": "Down",
        "device": "Keyboard",
        "hold": false,
        "doube_tap": false
      },
      {
        "button": "S",
        "device": "Keyboard",
        "hold": false,
        "doube_tap": false
      }
    ],
    "move_up": [
      {
        "button": "Up",
        "device": "Keyboard",
        "hold": false,
        "doube_tap": false
      },
      {
        "button": "W",
        "device": "Keyboard",
        "hold": false,
        "doube_tap": false
      }
    ]
  }
}